Metadata-Version: 2.1
Name: robogerctl
Version: 2.0.10
Summary: Roboger CLI tool and management library
Home-page: https://github.com/alttch/robogerctl
Author: Altertech
Author-email: pr@altertech.com
License: Apache License 2.0
Platform: UNKNOWN
Classifier: Programming Language :: Python :: 3
Classifier: License :: OSI Approved :: Apache Software License
Classifier: Topic :: Communications
